{
    "numero": "364.7",
    "sentido": true,
    "anomalia": false,
    "operadora": "EXPRESSO SÃO JOSÉ BACIA - 05",
    "tarifa": 2.7,
    "rota": {
        "circular": [
            [
                -15.794855,
                -48.110461
            ],
            [
                -15.794958000000001,
                -48.110308
            ],
            [
                -15.795010000000001,
                -48.110212000000004
            ],
            [
                -15.795052,
                -48.110083
            ],
            [
                -15.794956,
                -48.109992
            ],
            [
                -15.794941,
                -48.109962
            ],
            [
                -15.794943,
                -48.109929
            ],
            [
                -15.795003999999999,
                -48.109834
            ],
            [
                -15.795065999999998,
                -48.1097385
            ],
            [
                -15.795168744186045,
                -48.10958564534884
            ],
            [
                -15.79527148837209,
                -48.109432790697674
            ],
            [
                -15.795374232558139,
                -48.10927993604651
            ],
            [
                -15.795476976744185,
                -48.10912708139535
            ],
            [
                -15.795579720930231,
                -48.10897422674419
            ],
            [
                -15.795682465116277,
                -48.108821372093026
            ],
            [
                -15.795785209302323,
                -48.108668517441856
            ],
            [
                -15.795887953488371,
                -48.108515662790694
            ],
            [
                -15.795990697674418,
                -48.10836280813953
            ],
            [
                -15.796093441860464,
                -48.10820995348837
            ],
            [
                -15.79619618604651,
                -48.10805709883721
            ],
            [
                -15.796298930232558,
                -48.107904244186045
            ],
            [
                -15.796401674418604,
                -48.10775138953488
            ],
            [
                -15.79650441860465,
                -48.10759853488372
            ],
            [
                -15.796607162790696,
                -48.10744568023256
            ],
            [
                -15.796709906976742,
                -48.107292825581396
            ],
            [
                -15.79681265116279,
                -48.107139970930234
            ],
            [
                -15.796915395348837,
                -48.10698711627907
            ],
            [
                -15.797018139534883,
                -48.1068342616279
            ],
            [
                -15.797120883720929,
                -48.10668140697674
            ],
            [
                -15.797223627906975,
                -48.10652855232558
            ],
            [
                -15.797326372093023,
                -48.106375697674416
            ],
            [
                -15.79742911627907,
                -48.106222843023254
            ],
            [
                -15.797531860465115,
                -48.10606998837209
            ],
            [
                -15.797634604651162,
                -48.10591713372093
            ],
            [
                -15.797737348837208,
                -48.10576427906977
            ],
            [
                -15.797840093023256,
                -48.105611424418605
            ],
            [
                -15.797942837209302,
                -48.10545856976744
            ],
            [
                -15.798045581395348,
                -48.10530571511628
            ],
            [
                -15.798148325581394,
                -48.10515286046512
            ],
            [
                -15.79825106976744,
                -48.10500000581395
            ],
            [
                -15.798353813953488,
                -48.10484715116279
            ],
            [
                -15.798456558139534,
                -48.104694296511624
            ],
            [
                -15.79855930232558,
                -48.10454144186046
            ],
            [
                -15.798662046511627,
                -48.1043885872093
            ],
            [
                -15.798764790697675,
                -48.10423573255814
            ],
            [
                -15.79886753488372,
                -48.104082877906976
            ],
            [
                -15.798970279069767,
                -48.10393002325581
            ],
            [
                -15.799073023255813,
                -48.10377716860465
            ],
            [
                -15.79917576744186,
                -48.10362431395349
            ],
            [
                -15.799278511627907,
                -48.10347145930233
            ],
            [
                -15.799381255813953,
                -48.103318604651164
            ],
            [
                -15.799484,
                -48.10316575
            ],
            [
                -15.799586744186046,
                -48.10301289534883
            ],
            [
                -15.799689488372092,
                -48.10286004069767
            ],
            [
                -15.79979223255814,
                -48.10270718604651
            ],
            [
                -15.799894976744186,
                -48.102554331395346
            ],
            [
                -15.799997720930232,
                -48.102401476744184
            ],
            [
                -15.800100465116278,
                -48.10224862209302
            ],
            [
                -15.800203209302325,
                -48.10209576744186
            ],
            [
                -15.800305953488373,
                -48.1019429127907
            ],
            [
                -15.800408697674419,
                -48.101790058139535
            ],
            [
                -15.800511441860465,
                -48.10163720348837
            ],
            [
                -15.800614186046511,
                -48.10148434883721
            ],
            [
                -15.800716930232559,
                -48.10133149418605
            ],
            [
                -15.800819674418605,
                -48.10117863953488
            ],
            [
                -15.800922418604651,
                -48.10102578488372
            ],
            [
                -15.801025162790697,
                -48.100872930232555
            ],
            [
                -15.801127906976744,
                -48.10072007558139
            ],
            [
                -15.801230651162792,
                -48.10056722093023
            ],
            [
                -15.801333395348838,
                -48.10041436627907
            ],
            [
                -15.801436139534884,
                -48.100261511627906
            ],
            [
                -15.80153888372093,
                -48.100108656976744
            ],
            [
                -15.801641627906976,
                -48.09995580232558
            ],
            [
                -15.801744372093024,
                -48.09980294767442
            ],
            [
                -15.80184711627907,
                -48.09965009302326
            ],
            [
                -15.801949860465117,
                -48.099497238372095
            ],
            [
                -15.802052604651163,
                -48.099344383720926
            ],
            [
                -15.802155348837209,
                -48.09919152906976
            ],
            [
                -15.802258093023257,
                -48.0990386744186
            ],
            [
                -15.802360837209303,
                -48.09888581976744
            ],
            [
                -15.80246358139535,
                -48.09873296511628
            ],
            [
                -15.802566325581395,
                -48.098580110465115
            ],
            [
                -15.802669069767441,
                -48.09842725581395
            ],
            [
                -15.80277181395349,
                -48.09827440116279
            ],
            [
                -15.802874558139536,
                -48.09812154651163
            ],
            [
                -15.802977302325582,
                -48.097968691860466
            ],
            [
                -15.803080046511628,
                -48.0978158372093
            ],
            [
                -15.803182790697676,
                -48.09766298255814
            ],
            [
                -15.803285534883722,
                -48.09751012790697
            ],
            [
                -15.803388279069768,
                -48.09735727325581
            ],
            [
                -15.803491023255814,
                -48.09720441860465
            ],
            [
                -15.80359376744186,
                -48.097051563953485
            ],
            [
                -15.803696511627908,
                -48.09689870930232
            ],
            [
                -15.803799255813955,
                -48.09674585465116
            ],
            [
                -15.803880127906977,
                -48.09662692732558
            ],
            [
                -15.803983052713178,
                -48.09647406550388
            ],
            [
                -15.80408597751938,
                -48.09632120368217
            ],
            [
                -15.804188902325581,
                -48.09616834186046
            ],
            [
                -15.804291827131783,
                -48.09601548003876
            ],
            [
                -15.804394751937984,
                -48.095862618217055
            ],
            [
                -15.804497676744186,
                -48.09570975639535
            ],
            [
                -15.804600601550387,
                -48.09555689457365
            ],
            [
                -15.80470352635659,
                -48.09540403275194
            ],
            [
                -15.804806451162792,
                -48.09525117093023
            ],
            [
                -15.804909375968993,
                -48.09509830910853
            ],
            [
                -15.805012300775195,
                -48.094945447286825
            ],
            [
                -15.805115225581396,
                -48.09479258546512
            ],
            [
                -15.805218150387597,
                -48.09463972364341
            ],
            [
                -15.805321075193799,
                -48.09448686182171
            ],
            [
                -15.805420704721636,
                -48.094339692565185
            ],
            [
                -15.805520334249472,
                -48.09419252330867
            ],
            [
                -15.805619963777309,
                -48.09404535405215
            ],
            [
                -15.805719593305145,
                -48.093898184795634
            ],
            [
                -15.805819222832982,
                -48.09375101553911
            ],
            [
                -15.805918852360817,
                -48.0936038462826
            ],
            [
                -15.806018481888653,
                -48.093456677026076
            ],
            [
                -15.80611811141649,
                -48.09330950776956
            ],
            [
                -15.806217740944327,
                -48.09316233851304
            ],
            [
                -15.806317370472163,
                -48.093015169256525
            ],
            [
                -15.806414580314776,
                -48.09288577950435
            ],
            [
                -15.806511790157387,
                -48.092756389752175
            ],
            [
                -15.80660509261804,
                -48.09264529231413
            ],
            [
                -15.806698395078694,
                -48.09253419487609
            ],
            [
                -15.806791697539346,
                -48.092423097438044
            ],
            [
                -15.80688977315451,
                -48.09231782307853
            ],
            [
                -15.806987848769673,
                -48.09221254871902
            ],
            [
                -15.807085924384836,
                -48.09210727435951
            ],
            [
                -15.807177616256558,
                -48.09201751623968
            ],
            [
                -15.807269308128278,
                -48.09192775811984
            ],
            [
                -15.807373205418852,
                -48.09183383874656
            ],
            [
                -15.807477102709427,
                -48.091739919373275
            ],
            [
                -15.80760082703207,
                -48.09164168952996
            ],
            [
                -15.807724551354713,
                -48.09154345968663
            ],
            [
                -15.807848275677356,
                -48.091445229843316
            ],
            [
                -15.807964206758017,
                -48.09136292238249
            ],
            [
                -15.80808013783868,
                -48.09128061492166
            ],
            [
                -15.80819606891934,
                -48.09119830746083
            ],
            [
                -15.808309712612893,
                -48.09112553830722
            ],
            [
                -15.808423356306447,
                -48.09105276915361
            ],
            [
                -15.808569904204298,
                -48.09096984610241
            ],
            [
                -15.80871645210215,
                -48.0908869230512
            ],
            [
                -15.808850339076614,
                -48.0908189422884
            ],
            [
                -15.808984226051075,
                -48.0907509615256
            ],
            [
                -15.809118113025537,
                -48.0906829807628
            ],
            [
                -15.809250334769153,
                -48.0906267355721
            ],
            [
                -15.80938255651277,
                -48.090570490381396
            ],
            [
                -15.809514778256384,
                -48.0905142451907
            ],
            [
                -15.80965251883759,
                -48.09046083012713
            ],
            [
                -15.809790259418794,
                -48.09040741506357
            ],
            [
                -15.809900129709398,
                -48.090381207531784
            ],
            [
                -15.810078,
                -48.09037
            ],
            [
                -15.810208,
                -48.09048
            ],
            [
                -15.810270857142857,
                -48.09063485714286
            ],
            [
                -15.810333714285713,
                -48.09078971428571
            ],
            [
                -15.810396571428571,
                -48.09094457142857
            ],
            [
                -15.810459428571429,
                -48.091099428571425
            ],
            [
                -15.810522285714287,
                -48.091254285714285
            ],
            [
                -15.810585142857143,
                -48.09140914285714
            ],
            [
                -15.810648452380953,
                -48.09156061904761
            ],
            [
                -15.810711761904761,
                -48.091712095238094
            ],
            [
                -15.810775071428571,
                -48.09186357142857
            ],
            [
                -15.810838380952381,
                -48.09201504761904
            ],
            [
                -15.81090169047619,
                -48.092166523809524
            ],
            [
                -15.810969020408162,
                -48.092318020408165
            ],
            [
                -15.811036350340135,
                -48.092469517006805
            ],
            [
                -15.811103680272108,
                -48.092621013605445
            ],
            [
                -15.811171010204081,
                -48.09277251020408
            ],
            [
                -15.811238340136054,
                -48.09292400680272
            ],
            [
                -15.811305670068027,
                -48.09307550340136
            ],
            [
                -15.811365336054422,
                -48.09321560272109
            ],
            [
                -15.811425002040817,
                -48.09335570204082
            ],
            [
                -15.81148466802721,
                -48.09349580136054
            ],
            [
                -15.811544334013606,
                -48.09363590068027
            ],
            [
                -15.811622286297377,
                -48.09380162915452
            ],
            [
                -15.811700238581146,
                -48.09396735762876
            ],
            [
                -15.811778190864917,
                -48.094133086103014
            ],
            [
                -15.811856143148688,
                -48.09429881457726
            ],
            [
                -15.81193409543246,
                -48.09446454305151
            ],
            [
                -15.812012047716228,
                -48.09463027152575
            ],
            [
                -15.81209603181082,
                -48.09473184768383
            ],
            [
                -15.81218001590541,
                -48.09483342384192
            ],
            [
                -15.812257007952706,
                -48.094884711920955
            ],
            [
                -15.812375,
                -48.094906
            ],
            [
                -15.812402,
                -48.094854
            ],
            [
                -15.812399,
                -48.094777
            ],
            [
                -15.812399,
                -48.094701
            ],
            [
                -15.812323249999999,
                -48.094543
            ],
            [
                -15.8122475,
                -48.094385
            ],
            [
                -15.812171750000001,
                -48.094227
            ],
            [
                -15.812134875000002,
                -48.094116
            ],
            [
                -15.812116,
                -48.093959
            ],
            [
                -15.812143,
                -48.093927
            ],
            [
                -15.812191,
                -48.093895
            ],
            [
                -15.812235,
                -48.093874
            ],
            [
                -15.812405739837398,
                -48.09381569918699
            ],
            [
                -15.812576479674796,
                -48.09375739837398
            ],
            [
                -15.812747219512195,
                -48.09369909756097
            ],
            [
                -15.812917959349592,
                -48.09364079674797
            ],
            [
                -15.813088699186991,
                -48.09358249593496
            ],
            [
                -15.813259439024389,
                -48.09352419512195
            ],
            [
                -15.813430178861788,
                -48.09346589430894
            ],
            [
                -15.813600918699187,
                -48.09340759349593
            ],
            [
                -15.813771658536584,
                -48.09334929268292
            ],
            [
                -15.813942398373984,
                -48.09329099186992
            ],
            [
                -15.81411313821138,
                -48.09323269105691
            ],
            [
                -15.81428387804878,
                -48.0931743902439
            ],
            [
                -15.81445461788618,
                -48.09311608943089
            ],
            [
                -15.814625357723576,
                -48.093057788617884
            ],
            [
                -15.814796097560976,
                -48.092999487804875
            ],
            [
                -15.814966837398373,
                -48.09294118699187
            ],
            [
                -15.815137577235772,
                -48.09288288617886
            ],
            [
                -15.81530831707317,
                -48.092824585365854
            ],
            [
                -15.815479056910569,
                -48.092766284552845
            ],
            [
                -15.815649796747968,
                -48.092707983739835
            ],
            [
                -15.815820536585365,
                -48.092649682926826
            ],
            [
                -15.815991276422764,
                -48.092591382113824
            ],
            [
                -15.816162016260161,
                -48.092533081300815
            ],
            [
                -15.81633275609756,
                -48.092474780487805
            ],
            [
                -15.816503495934958,
                -48.092416479674796
            ],
            [
                -15.816674235772357,
                -48.09235817886179
            ],
            [
                -15.816844975609756,
                -48.09229987804878
            ],
            [
                -15.817015715447154,
                -48.092241577235775
            ],
            [
                -15.817186455284553,
                -48.092183276422766
            ],
            [
                -15.81735719512195,
                -48.09212497560976
            ],
            [
                -15.81752793495935,
                -48.09206667479675
            ],
            [
                -15.817698674796747,
                -48.09200837398374
            ],
            [
                -15.817869414634146,
                -48.09195007317073
            ],
            [
                -15.818040154471545,
                -48.09189177235773
            ],
            [
                -15.818210894308942,
                -48.09183347154472
            ],
            [
                -15.818381634146341,
                -48.09177517073171
            ],
            [
                -15.818552373983739,
                -48.0917168699187
            ],
            [
                -15.818723113821138,
                -48.09165856910569
            ],
            [
                -15.818893853658537,
                -48.09160026829268
            ],
            [
                -15.819064593495934,
                -48.09154196747968
            ],
            [
                -15.819235333333333,
                -48.09148366666667
            ],
            [
                -15.81940607317073,
                -48.09142536585366
            ],
            [
                -15.81957681300813,
                -48.09136706504065
            ],
            [
                -15.819747552845527,
                -48.09130876422764
            ],
            [
                -15.819918292682926,
                -48.09125046341463
            ],
            [
                -15.820089032520325,
                -48.09119216260162
            ],
            [
                -15.820259772357723,
                -48.09113386178862
            ],
            [
                -15.820430512195122,
                -48.09107556097561
            ],
            [
                -15.82060125203252,
                -48.0910172601626
            ],
            [
                -15.820771991869918,
                -48.09095895934959
            ],
            [
                -15.820942731707316,
                -48.09090065853658
            ],
            [
                -15.821113471544715,
                -48.090842357723574
            ],
            [
                -15.821284211382114,
                -48.09078405691057
            ],
            [
                -15.821454951219511,
                -48.09072575609756
            ],
            [
                -15.82162569105691,
                -48.09066745528455
            ],
            [
                -15.821796430894308,
                -48.090609154471544
            ],
            [
                -15.821967170731707,
                -48.090550853658534
            ],
            [
                -15.822137910569104,
                -48.090492552845525
            ],
            [
                -15.822308650406503,
                -48.09043425203252
            ],
            [
                -15.822479390243902,
                -48.090375951219514
            ],
            [
                -15.8226501300813,
                -48.090317650406504
            ],
            [
                -15.822820869918699,
                -48.090259349593495
            ],
            [
                -15.822991609756096,
                -48.090201048780486
            ],
            [
                -15.823162349593495,
                -48.09014274796748
            ],
            [
                -15.823333089430895,
                -48.090084447154474
            ],
            [
                -15.823503829268292,
                -48.090026146341465
            ],
            [
                -15.823674569105691,
                -48.089967845528456
            ],
            [
                -15.823845308943088,
                -48.08990954471545
            ],
            [
                -15.824016048780488,
                -48.08985124390244
            ],
            [
                -15.824186788617885,
                -48.08979294308943
            ],
            [
                -15.824357528455284,
                -48.089734642276426
            ],
            [
                -15.824528268292683,
                -48.08967634146342
            ],
            [
                -15.82469900813008,
                -48.08961804065041
            ],
            [
                -15.82486974796748,
                -48.0895597398374
            ],
            [
                -15.825040487804877,
                -48.08950143902439
            ],
            [
                -15.825211227642276,
                -48.08944313821138
            ],
            [
                -15.825381967479673,
                -48.08938483739838
            ],
            [
                -15.825552707317073,
                -48.08932653658537
            ],
            [
                -15.825723447154472,
                -48.08926823577236
            ],
            [
                -15.825894186991869,
                -48.08920993495935
            ],
            [
                -15.826064926829268,
                -48.08915163414634
            ],
            [
                -15.826235666666665,
                -48.08909333333333
            ],
            [
                -15.826406406504065,
                -48.08903503252032
            ],
            [
                -15.826577146341462,
                -48.08897673170732
            ],
            [
                -15.826747886178861,
                -48.08891843089431
            ],
            [
                -15.82691862601626,
                -48.0888601300813
            ],
            [
                -15.827089365853658,
                -48.08880182926829
            ],
            [
                -15.827260105691057,
                -48.08874352845528
            ],
            [
                -15.827430845528454,
                -48.08868522764227
            ],
            [
                -15.827601585365853,
                -48.08862692682927
            ],
            [
                -15.827772325203252,
                -48.08856862601626
            ],
            [
                -15.82794306504065,
                -48.08851032520325
            ],
            [
                -15.828113804878049,
                -48.08845202439024
            ],
            [
                -15.828284544715446,
                -48.088393723577234
            ],
            [
                -15.828455284552845,
                -48.088335422764224
            ],
            [
                -15.828626024390243,
                -48.08827712195122
            ],
            [
                -15.828796764227642,
                -48.08821882113821
            ],
            [
                -15.82896750406504,
                -48.088160520325204
            ],
            [
                -15.829138243902438,
                -48.088102219512194
            ],
            [
                -15.829308983739837,
                -48.088043918699185
            ],
            [
                -15.829479723577235,
                -48.087985617886176
            ],
            [
                -15.829650463414634,
                -48.087927317073174
            ],
            [
                -15.829821203252031,
                -48.087869016260164
            ],
            [
                -15.82999194308943,
                -48.087810715447155
            ],
            [
                -15.83016268292683,
                -48.087752414634146
            ],
            [
                -15.830333422764227,
                -48.08769411382114
            ],
            [
                -15.830504162601626,
                -48.08763581300813
            ],
            [
                -15.830674902439023,
                -48.087577512195125
            ],
            [
                -15.830845642276422,
                -48.087519211382116
            ],
            [
                -15.83101638211382,
                -48.087460910569106
            ],
            [
                -15.831187121951219,
                -48.0874026097561
            ],
            [
                -15.831357861788618,
                -48.08734430894309
            ],
            [
                -15.831528601626015,
                -48.08728600813008
            ],
            [
                -15.831699341463414,
                -48.087227707317076
            ],
            [
                -15.831870081300812,
                -48.08716940650407
            ],
            [
                -15.83204082113821,
                -48.08711110569106
            ],
            [
                -15.83221156097561,
                -48.08705280487805
            ],
            [
                -15.832382300813007,
                -48.08699450406504
            ],
            [
                -15.832553040650406,
                -48.08693620325203
            ],
            [
                -15.832723780487804,
                -48.08687790243903
            ],
            [
                -15.832894520325203,
                -48.08681960162602
            ],
            [
                -15.8330652601626,
                -48.08676130081301
            ],
            [
                -15.8332316300813,
                -48.0867051504065
            ],
            [
                -15.833388176321138,
                -48.086653381605686
            ],
            [
                -15.833544722560976,
                -48.08660161280488
            ],
            [
                -15.833701268800812,
                -48.08654984400407
            ],
            [
                -15.83385781504065,
                -48.08649807520325
            ],
            [
                -15.834014361280488,
                -48.086446306402436
            ],
            [
                -15.834170907520324,
                -48.08639453760163
            ],
            [
                -15.834327453760162,
                -48.08634276880082
            ],
            [
                -15.834475340320122,
                -48.08629282660061
            ],
            [
                -15.83462322688008,
                -48.086242884400406
            ],
            [
                -15.83477111344004,
                -48.086192942200206
            ],
            [
                -15.83489655672002,
                -48.0861599711001
            ],
            [
                -15.835074,
                -48.086134
            ],
            [
                -15.835141,
                -48.086191
            ],
            [
                -15.835197,
                -48.086331
            ],
            [
                -15.835223000000001,
                -48.086462
            ],
            [
                -15.835249,
                -48.086593
            ],
            [
                -15.835284999999999,
                -48.08675625
            ],
            [
                -15.835321,
                -48.0869195
            ],
            [
                -15.835357,
                -48.08708275
            ],
            [
                -15.835399166666667,
                -48.087253958333335
            ],
            [
                -15.835441333333334,
                -48.08742516666667
            ],
            [
                -15.8354835,
                -48.087596375000004
            ],
            [
                -15.835525666666667,
                -48.08776758333333
            ],
            [
                -15.835567833333334,
                -48.087938791666666
            ],
            [
                -15.835610875,
                -48.08809534375
            ],
            [
                -15.835653916666667,
                -48.08825189583334
            ],
            [
                -15.835696958333333,
                -48.08840844791667
            ],
            [
                -15.83574646875,
                -48.0885780859375
            ],
            [
                -15.835795979166667,
                -48.088747723958335
            ],
            [
                -15.835845489583335,
                -48.08891736197917
            ],
            [
                -15.835919744791667,
                -48.089082180989585
            ],
            [
                -15.835990872395833,
                -48.08922609049479
            ],
            [
                -15.836055436197917,
                -48.089346545247395
            ],
            [
                -15.836120218098959,
                -48.0894817726237
            ],
            [
                -15.836165478732639,
                -48.0895988484158
            ],
            [
                -15.83621073936632,
                -48.0897159242079
            ],
            [
                -15.836265826244214,
                -48.089865949471935
            ],
            [
                -15.836320913122107,
                -48.09001597473597
            ],
            [
                -15.836369608748072,
                -48.09015931649065
            ],
            [
                -15.836418304374035,
                -48.09030265824532
            ],
            [
                -15.836474152187018,
                -48.09041032912266
            ],
            [
                -15.836584,
                -48.090546
            ],
            [
                -15.836636,
                -48.090554
            ],
            [
                -15.836757,
                -48.090505
            ],
            [
                -15.836783,
                -48.090449
            ],
            [
                -15.836801,
                -48.090404
            ],
            [
                -15.83679,
                -48.090312
            ],
            [
                -15.836736250000001,
                -48.090151
            ],
            [
                -15.8366825,
                -48.08999
            ],
            [
                -15.83662875,
                -48.089829
            ],
            [
                -15.836578175,
                -48.0896612
            ],
            [
                -15.8365276,
                -48.0894934
            ],
            [
                -15.836477024999999,
                -48.0893256
            ],
            [
                -15.83642645,
                -48.0891578
            ],
            [
                -15.836375875,
                -48.08899
            ],
            [
                -15.8363253,
                -48.0888222
            ],
            [
                -15.836274725,
                -48.0886544
            ],
            [
                -15.83622415,
                -48.0884866
            ],
            [
                -15.836173575,
                -48.0883188
            ],
            [
                -15.836131479166667,
                -48.088154333333335
            ],
            [
                -15.836089383333334,
                -48.08798986666667
            ],
            [
                -15.836047287500001,
                -48.0878254
            ],
            [
                -15.836005191666667,
                -48.08766093333334
            ],
            [
                -15.835963095833334,
                -48.08749646666667
            ],
            [
                -15.835934063888889,
                -48.08733231111111
            ],
            [
                -15.835905031944446,
                -48.08716815555556
            ],
            [
                -15.835902015972223,
                -48.08702307777778
            ],
            [
                -15.835867414375,
                -48.08683987
            ],
            [
                -15.83583281277778,
                -48.086656662222225
            ],
            [
                -15.835798211180556,
                -48.086473454444445
            ],
            [
                -15.835763609583335,
                -48.08629024666667
            ],
            [
                -15.835729007986112,
                -48.08610703888889
            ],
            [
                -15.835694406388889,
                -48.08592383111111
            ],
            [
                -15.835659804791668,
                -48.085740623333336
            ],
            [
                -15.835625203194445,
                -48.085557415555556
            ],
            [
                -15.835590601597223,
                -48.08537420777778
            ],
            [
                -15.835562081277779,
                -48.08521296622222
            ],
            [
                -15.835533560958334,
                -48.08505172466667
            ],
            [
                -15.835505040638889,
                -48.08489048311111
            ],
            [
                -15.835476520319444,
                -48.08472924155556
            ],
            [
                -15.835445874559523,
                -48.08456020704762
            ],
            [
                -15.835415228799603,
                -48.08439117253968
            ],
            [
                -15.835384583039682,
                -48.08422213803175
            ],
            [
                -15.835353937279763,
                -48.08405310352381
            ],
            [
                -15.835323291519842,
                -48.08388406901587
            ],
            [
                -15.835292645759921,
                -48.08371503450793
            ],
            [
                -15.835293097173281,
                -48.08353535633862
            ],
            [
                -15.83529354858664,
                -48.08335567816931
            ],
            [
                -15.835271290488866,
                -48.08318489847443
            ],
            [
                -15.835249032391093,
                -48.083014118779545
            ],
            [
                -15.83522677429332,
                -48.08284333908466
            ],
            [
                -15.835204516195546,
                -48.08267255938977
            ],
            [
                -15.835182258097774,
                -48.08250177969489
            ],
            [
                -15.835167129048887,
                -48.08235038984745
            ],
            [
                -15.835145064524443,
                -48.082204694923725
            ],
            [
                -15.835123532262221,
                -48.082070347461865
            ],
            [
                -15.83506226613111,
                -48.08189967373093
            ],
            [
                -15.83500817742074,
                -48.08178744915396
            ],
            [
                -15.83495408871037,
                -48.081675224576976
            ],
            [
                -15.834921073925308,
                -48.081515853814146
            ],
            [
                -15.834888059140248,
                -48.081356483051316
            ],
            [
                -15.834855044355185,
                -48.08119711228849
            ],
            [
                -15.834822029570123,
                -48.08103774152566
            ],
            [
                -15.834789014785063,
                -48.08087837076283
            ],
            [
                -15.834767009856709,
                -48.08071024717522
            ],
            [
                -15.834745004928354,
                -48.08054212358761
            ],
            [
                -15.83473267077363,
                -48.08038443632301
            ],
            [
                -15.834720336618902,
                -48.08022674905841
            ],
            [
                -15.834708002464177,
                -48.08006906179381
            ],
            [
                -15.834695668309452,
                -48.0799113745292
            ],
            [
                -15.834683334154725,
                -48.079753687264606
            ],
            [
                -15.834681429275479,
                -48.07957873194109
            ],
            [
                -15.834679524396233,
                -48.079403776617575
            ],
            [
                -15.834677619516986,
                -48.07922882129406
            ],
            [
                -15.834675714637738,
                -48.07905386597055
            ],
            [
                -15.834673809758492,
                -48.078878910647035
            ],
            [
                -15.834671904879245,
                -48.07870395532352
            ],
            [
                -15.834684936586164,
                -48.078554636882345
            ],
            [
                -15.834697968293082,
                -48.07840531844118
            ],
            [
                -15.834735312195388,
                -48.078245878960786
            ],
            [
                -15.834772656097693,
                -48.078086439480394
            ],
            [
                -15.834836724878155,
                -48.07794655158432
            ],
            [
                -15.834900793658615,
                -48.077806663688236
            ],
            [
                -15.834964862439078,
                -48.07766677579216
            ],
            [
                -15.835028931219538,
                -48.07752688789608
            ],
            [
                -15.835101198414653,
                -48.07740466592206
            ],
            [
                -15.835173465609769,
                -48.077282443948036
            ],
            [
                -15.835245732804884,
                -48.07716022197402
            ],
            [
                -15.835313155203256,
                -48.076994814649346
            ],
            [
                -15.835380577601628,
                -48.076829407324674
            ],
            [
                -15.835428051734418,
                -48.07666327154978
            ],
            [
                -15.83547552586721,
                -48.07649713577489
            ],
            [
                -15.835501017244807,
                -48.0763700905166
            ],
            [
                -15.835526508622403,
                -48.076243045258295
            ],
            [
                -15.835544254311202,
                -48.07607502262915
            ],
            [
                -15.835557627155602,
                -48.07591401131457
            ],
            [
                -15.835557084770402,
                -48.07576800754305
            ],
            [
                -15.8355565423852,
                -48.07562200377153
            ],
            [
                -15.8355432711926,
                -48.07545250188576
            ],
            [
                -15.83551570339445,
                -48.075312376414324
            ],
            [
                -15.8354881355963,
                -48.075172250942884
            ],
            [
                -15.835460567798151,
                -48.07503212547144
            ],
            [
                -15.8354493785321,
                -48.07490208364762
            ],
            [
                -15.83543818926605,
                -48.07477204182381
            ],
            [
                -15.835460094633024,
                -48.07462052091191
            ],
            [
                -15.835510547316513,
                -48.074489760455954
            ],
            [
                -15.835570773658256,
                -48.07439638022798
            ],
            [
                -15.835650386829128,
                -48.07433769011399
            ],
            [
                -15.835754193414564,
                -48.074306345056996
            ],
            [
                -15.835863096707282,
                -48.0743041725285
            ],
            [
                -15.83595754835364,
                -48.07433408626425
            ],
            [
                -15.83604477417682,
                -48.07438954313213
            ],
            [
                -15.83611338708841,
                -48.07446377156606
            ],
            [
                -15.836158693544206,
                -48.07457038578303
            ],
            [
                -15.836168346772103,
                -48.07469669289152
            ],
            [
                -15.836141673386052,
                -48.07482034644576
            ],
            [
                -15.836092836693027,
                -48.07491817322288
            ],
            [
                -15.836029918346513,
                -48.074998086611444
            ],
            [
                -15.835896959173256,
                -48.07510054330572
            ],
            [
                -15.835774979586628,
                -48.075204771652864
            ],
            [
                -15.83563173468997,
                -48.075310578739646
            ],
            [
                -15.835488489793313,
                -48.07541638582643
            ],
            [
                -15.835345244896658,
                -48.07552219291322
            ],
            [
                -15.83518212244833,
                -48.07559509645661
            ],
            [
                -15.835039561224164,
                -48.07564004822831
            ],
            [
                -15.834889280612082,
                -48.075652024114156
            ],
            [
                -15.834737640306042,
                -48.07559801205708
            ],
            [
                -15.83461932015302,
                -48.075496006028544
            ],
            [
                -15.834614405133893,
                -48.075331005274975
            ],
            [
                -15.834609490114765,
                -48.07516600452141
            ],
            [
                -15.834604575095637,
                -48.07500100376784
            ],
            [
                -15.83459966007651,
                -48.07483600301427
            ],
            [
                -15.834594745057384,
                -48.07467100226071
            ],
            [
                -15.834589830038256,
                -48.07450600150714
            ],
            [
                -15.834584915019128,
                -48.07434100075357
            ],
            [
                -15.834597457509563,
                -48.07420400037678
            ],
            [
                -15.834630728754782,
                -48.07410150018839
            ],
            [
                -15.83468936437739,
                -48.0740287500942
            ],
            [
                -15.834822,
                -48.073957
            ],
            [
                -15.834901,
                -48.07399
            ],
            [
                -15.834983,
                -48.074103
            ],
            [
                -15.835049999999999,
                -48.0742245
            ],
            [
                -15.8350928,
                -48.074379
            ],
            [
                -15.8351356,
                -48.0745335
            ],
            [
                -15.8351784,
                -48.074688
            ],
            [
                -15.8352212,
                -48.0748425
            ],
            [
                -15.83525165,
                -48.074982875
            ],
            [
                -15.8352821,
                -48.075123250000004
            ],
            [
                -15.83531255,
                -48.075263625
            ],
            [
                -15.835331366666667,
                -48.07539108333333
            ],
            [
                -15.835350183333333,
                -48.07551854166667
            ],
            [
                -15.835357455555554,
                -48.07566802777778
            ],
            [
                -15.835364727777778,
                -48.075817513888886
            ],
            [
                -15.835357151851852,
                -48.075960009259255
            ],
            [
                -15.835349575925926,
                -48.07610250462963
            ],
            [
                -15.83532871728395,
                -48.076249003086424
            ],
            [
                -15.835307858641976,
                -48.07639550154321
            ],
            [
                -15.83526188691358,
                -48.07654980123457
            ],
            [
                -15.835215915185184,
                -48.07670410092593
            ],
            [
                -15.83516994345679,
                -48.07685840061728
            ],
            [
                -15.835123971728395,
                -48.07701270030864
            ],
            [
                -15.835046981152264,
                -48.077172466872426
            ],
            [
                -15.83496999057613,
                -48.077332233436216
            ],
            [
                -15.834894242932098,
                -48.07748367507716
            ],
            [
                -15.834818495288065,
                -48.07763511671811
            ],
            [
                -15.834742747644032,
                -48.07778655835906
            ],
            [
                -15.834690810733024,
                -48.077937918769294
            ],
            [
                -15.834638873822016,
                -48.07808927917953
            ],
            [
                -15.834586936911009,
                -48.078240639589765
            ],
            [
                -15.834551349528807,
                -48.07841591167181
            ],
            [
                -15.834515762146605,
                -48.07859118375386
            ],
            [
                -15.834480174764405,
                -48.078766455835904
            ],
            [
                -15.834444587382203,
                -48.07894172791795
            ],
            [
                -15.834416069905762,
                -48.07908898233436
            ],
            [
                -15.834387552429321,
                -48.07923623675077
            ],
            [
                -15.83435903495288,
                -48.07938349116718
            ],
            [
                -15.83433051747644,
                -48.07953074558359
            ],
            [
                -15.834306011650959,
                -48.07967816372239
            ],
            [
                -15.83428150582548,
                -48.0798255818612
            ],
            [
                -15.8342780881879,
                -48.080001151551
            ],
            [
                -15.83427467055032,
                -48.080176721240804
            ],
            [
                -15.834271252912739,
                -48.080352290930605
            ],
            [
                -15.83426783527516,
                -48.0805278606204
            ],
            [
                -15.83426441763758,
                -48.0807034303102
            ],
            [
                -15.834284334110064,
                -48.08087074424816
            ],
            [
                -15.834304250582548,
                -48.08103805818612
            ],
            [
                -15.834324167055033,
                -48.08120537212408
            ],
            [
                -15.834344083527517,
                -48.08137268606204
            ],
            [
                -15.834364666822013,
                -48.08152974884963
            ],
            [
                -15.83438525011651,
                -48.081686811637226
            ],
            [
                -15.834405833411008,
                -48.08184387442481
            ],
            [
                -15.834426416705504,
                -48.082000937212406
            ],
            [
                -15.83445674245955,
                -48.08218403382946
            ],
            [
                -15.834487068213594,
                -48.082367130446514
            ],
            [
                -15.834517393967639,
                -48.08255022706357
            ],
            [
                -15.834547719721684,
                -48.08273332368062
            ],
            [
                -15.834578045475729,
                -48.08291642029768
            ],
            [
                -15.834608371229775,
                -48.08309951691473
            ],
            [
                -15.83463869698382,
                -48.083282613531786
            ],
            [
                -15.834669022737865,
                -48.083465710148836
            ],
            [
                -15.83469934849191,
                -48.08364880676589
            ],
            [
                -15.834729674245954,
                -48.08383190338294
            ],
            [
                -15.834762158405413,
                -48.08401218489359
            ],
            [
                -15.834794642564871,
                -48.084192466404225
            ],
            [
                -15.834827126724331,
                -48.08437274791487
            ],
            [
                -15.83485961088379,
                -48.08455302942551
            ],
            [
                -15.834892095043248,
                -48.08473331093615
            ],
            [
                -15.834924579202706,
                -48.08491359244679
            ],
            [
                -15.834957063362165,
                -48.08509387395743
            ],
            [
                -15.834989547521623,
                -48.08527415546807
            ],
            [
                -15.835022031681083,
                -48.085454436978715
            ],
            [
                -15.835054515840541,
                -48.08563471848935
            ],
            [
                -15.835060757920271,
                -48.08579485924467
            ],
            [
                -15.835028378960136,
                -48.08592092962233
            ],
            [
                -15.834968689480068,
                -48.08600096481116
            ],
            [
                -15.83484351711005,
                -48.08606072360837
            ],
            [
                -15.834718344740033,
                -48.086120482405576
            ],
            [
                -15.834593172370017,
                -48.08618024120279
            ],
            [
                -15.834441775823764,
                -48.08623121105244
            ],
            [
                -15.834290379277512,
                -48.08628218090209
            ],
            [
                -15.834138982731261,
                -48.08633315075174
            ],
            [
                -15.833987586185009,
                -48.086384120601394
            ],
            [
                -15.833836189638756,
                -48.08643509045105
            ],
            [
                -15.833684793092505,
                -48.0864860603007
            ],
            [
                -15.833533396546253,
                -48.086537030150346
            ],
            [
                -15.833379698273127,
                -48.08658801507517
            ],
            [
                -15.833210236686941,
                -48.08664607895457
            ],
            [
                -15.833040775100757,
                -48.086704142833966
            ],
            [
                -15.832871313514572,
                -48.08676220671337
            ],
            [
                -15.832701851928388,
                -48.08682027059277
            ],
            [
                -15.832532390342202,
                -48.08687833447217
            ],
            [
                -15.832362928756018,
                -48.08693639835156
            ],
            [
                -15.832193467169832,
                -48.08699446223096
            ],
            [
                -15.832024005583648,
                -48.08705252611036
            ],
            [
                -15.831854543997462,
                -48.08711058998976
            ],
            [
                -15.831685082411276,
                -48.087168653869156
            ],
            [
                -15.831515620825092,
                -48.08722671774856
            ],
            [
                -15.831346159238906,
                -48.08728478162796
            ],
            [
                -15.831176697652722,
                -48.08734284550735
            ],
            [
                -15.831007236066537,
                -48.08740090938675
            ],
            [
                -15.830837774480353,
                -48.08745897326615
            ],
            [
                -15.830668312894167,
                -48.08751703714555
            ],
            [
                -15.830498851307981,
                -48.087575101024946
            ],
            [
                -15.830329389721797,
                -48.08763316490435
            ],
            [
                -15.830159928135611,
                -48.08769122878375
            ],
            [
                -15.829990466549427,
                -48.08774929266315
            ],
            [
                -15.829821004963241,
                -48.08780735654254
            ],
            [
                -15.829651543377057,
                -48.08786542042194
            ],
            [
                -15.829482081790871,
                -48.08792348430134
            ],
            [
                -15.829312620204687,
                -48.087981548180736
            ],
            [
                -15.829143158618502,
                -48.088039612060136
            ],
            [
                -15.828973697032316,
                -48.08809767593954
            ],
            [
                -15.828804235446132,
                -48.08815573981894
            ],
            [
                -15.828634773859946,
                -48.08821380369833
            ],
            [
                -15.828465312273762,
                -48.08827186757773
            ],
            [
                -15.828295850687576,
                -48.08832993145713
            ],
            [
                -15.828126389101392,
                -48.08838799533653
            ],
            [
                -15.827956927515206,
                -48.088446059215926
            ],
            [
                -15.827787465929022,
                -48.088504123095326
            ],
            [
                -15.827618004342836,
                -48.08856218697473
            ],
            [
                -15.82744854275665,
                -48.08862025085412
            ],
            [
                -15.827279081170467,
                -48.08867831473352
            ],
            [
                -15.82710961958428,
                -48.08873637861292
            ],
            [
                -15.826940157998097,
                -48.08879444249232
            ],
            [
                -15.826770696411911,
                -48.088852506371715
            ],
            [
                -15.826601234825727,
                -48.088910570251116
            ],
            [
                -15.826431773239541,
                -48.08896863413052
            ],
            [
                -15.826262311653355,
                -48.08902669800992
            ],
            [
                -15.826092850067171,
                -48.08908476188931
            ],
            [
                -15.825923388480986,
                -48.08914282576871
            ],
            [
                -15.825753926894802,
                -48.08920088964811
            ],
            [
                -15.825584465308616,
                -48.089258953527505
            ],
            [
                -15.825415003722432,
                -48.089317017406906
            ],
            [
                -15.825245542136246,
                -48.089375081286306
            ],
            [
                -15.825076080550062,
                -48.08943314516571
            ],
            [
                -15.824906618963876,
                -48.0894912090451
            ],
            [
                -15.82473715737769,
                -48.0895492729245
            ],
            [
                -15.824567695791506,
                -48.0896073368039
            ],
            [
                -15.82439823420532,
                -48.0896654006833
            ],
            [
                -15.824228772619136,
                -48.089723464562695
            ],
            [
                -15.82405931103295,
                -48.089781528442096
            ],
            [
                -15.823889849446767,
                -48.089839592321496
            ],
            [
                -15.82372038786058,
                -48.08989765620089
            ],
            [
                -15.823550926274397,
                -48.08995572008029
            ],
            [
                -15.823381464688211,
                -48.09001378395969
            ],
            [
                -15.823212003102025,
                -48.09007184783909
            ],
            [
                -15.823042541515841,
                -48.090129911718485
            ],
            [
                -15.822873079929655,
                -48.090187975597885
            ],
            [
                -15.822703618343471,
                -48.090246039477286
            ],
            [
                -15.822534156757285,
                -48.09030410335669
            ],
            [
                -15.822364695171101,
                -48.09036216723608
            ],
            [
                -15.822195233584916,
                -48.09042023111548
            ],
            [
                -15.82202577199873,
                -48.09047829499488
            ],
            [
                -15.821856310412546,
                -48.09053635887428
            ],
            [
                -15.82168684882636,
                -48.090594422753675
            ],
            [
                -15.821517387240176,
                -48.090652486633076
            ],
            [
                -15.82134792565399,
                -48.090710550512476
            ],
            [
                -15.821178464067806,
                -48.09076861439187
            ],
            [
                -15.82100900248162,
                -48.09082667827127
            ],
            [
                -15.820839540895436,
                -48.09088474215067
            ],
            [
                -15.82067007930925,
                -48.09094280603007
            ],
            [
                -15.820500617723065,
                -48.091000869909465
            ],
            [
                -15.82033115613688,
                -48.091058933788865
            ],
            [
                -15.820161694550695,
                -48.091116997668266
            ],
            [
                -15.81999223296451,
                -48.091175061547666
            ],
            [
                -15.819822771378325,
                -48.09123312542706
            ],
            [
                -15.819653309792141,
                -48.09129118930646
            ],
            [
                -15.819483848205955,
                -48.09134925318586
            ],
            [
                -15.819314386619771,
                -48.091407317065254
            ],
            [
                -15.819144925033585,
                -48.091465380944655
            ],
            [
                -15.8189754634474,
                -48.091523444824055
            ],
            [
                -15.818806001861216,
                -48.091581508703456
            ],
            [
                -15.81863654027503,
                -48.09163957258285
            ],
            [
                -15.818467078688846,
                -48.09169763646225
            ],
            [
                -15.81829761710266,
                -48.09175570034165
            ],
            [
                -15.818128155516476,
                -48.09181376422105
            ],
            [
                -15.81795869393029,
                -48.091871828100444
            ],
            [
                -15.817789232344104,
                -48.091929891979845
            ],
            [
                -15.81761977075792,
                -48.091987955859246
            ],
            [
                -15.817450309171734,
                -48.09204601973864
            ],
            [
                -15.81728084758555,
                -48.09210408361804
            ],
            [
                -15.817111385999365,
                -48.09216214749744
            ],
            [
                -15.81694192441318,
                -48.09222021137684
            ],
            [
                -15.816772462826995,
                -48.092278275256234
            ],
            [
                -15.81660300124081,
                -48.092336339135635
            ],
            [
                -15.816433539654625,
                -48.092394403015035
            ],
            [
                -15.81626407806844,
                -48.092452466894436
            ],
            [
                -15.816094616482255,
                -48.09251053077383
            ],
            [
                -15.81592515489607,
                -48.09256859465323
            ],
            [
                -15.815755693309885,
                -48.09262665853263
            ],
            [
                -15.8155862317237,
                -48.092684722412024
            ],
            [
                -15.815416770137515,
                -48.092742786291424
            ],
            [
                -15.81524730855133,
                -48.092800850170825
            ],
            [
                -15.815077846965146,
                -48.092858914050225
            ],
            [
                -15.81490838537896,
                -48.09291697792962
            ],
            [
                -15.814738923792774,
                -48.09297504180902
            ],
            [
                -15.81456946220659,
                -48.09303310568842
            ],
            [
                -15.814400000620404,
                -48.09309116956782
            ],
            [
                -15.81423053903422,
                -48.093149233447214
            ],
            [
                -15.814061077448034,
                -48.093207297326614
            ],
            [
                -15.81389161586185,
                -48.093265361206015
            ],
            [
                -15.813722154275665,
                -48.09332342508541
            ],
            [
                -15.813552692689479,
                -48.09338148896481
            ],
            [
                -15.813383231103295,
                -48.09343955284421
            ],
            [
                -15.813213769517109,
                -48.09349761672361
            ],
            [
                -15.813044307930925,
                -48.093555680603004
            ],
            [
                -15.812874846344739,
                -48.093613744482404
            ],
            [
                -15.812705384758555,
                -48.093671808361805
            ],
            [
                -15.81253592317237,
                -48.093729872241205
            ],
            [
                -15.812366461586185,
                -48.0937879361206
            ],
            [
                -15.812233230793092,
                -48.0938254680603
            ],
            [
                -15.812135615396546,
                -48.09384273403015
            ],
            [
                -15.81199,
                -48.093851
            ],
            [
                -15.81192275,
                -48.0937085
            ],
            [
                -15.8118555,
                -48.093565999999996
            ],
            [
                -15.81178825,
                -48.0934235
            ],
            [
                -15.811715395833332,
                -48.093254125
            ],
            [
                -15.811642541666666,
                -48.09308475
            ],
            [
                -15.8115696875,
                -48.092915375000004
            ],
            [
                -15.811496833333333,
                -48.092746
            ],
            [
                -15.811423979166666,
                -48.092576625
            ],
            [
                -15.811351125,
                -48.09240725
            ],
            [
                -15.811278270833334,
                -48.092237875
            ],
            [
                -15.811205416666667,
                -48.0920685
            ],
            [
                -15.8111325625,
                -48.091899125
            ],
            [
                -15.811059708333334,
                -48.09172975
            ],
            [
                -15.810986854166668,
                -48.091560375
            ],
            [
                -15.810923247395834,
                -48.091400953125
            ],
            [
                -15.810859640625,
                -48.09124153125
            ],
            [
                -15.810796033854167,
                -48.091082109375
            ],
            [
                -15.810732427083334,
                -48.0909226875
            ],
            [
                -15.8106688203125,
                -48.090763265625
            ],
            [
                -15.810605213541667,
                -48.09060384375
            ],
            [
                -15.810541606770833,
                -48.090444421875
            ],
            [
                -15.810488205078125,
                -48.090304566406246
            ],
            [
                -15.810434803385416,
                -48.0901647109375
            ],
            [
                -15.810381401692709,
                -48.090024855468755
            ],
            [
                -15.810321601128473,
                -48.08986523697917
            ],
            [
                -15.810261800564236,
                -48.08970561848958
            ],
            [
                -15.810207850423177,
                -48.08955771386719
            ],
            [
                -15.810153900282117,
                -48.08940980924479
            ],
            [
                -15.810099950141058,
                -48.0892619046224
            ],
            [
                -15.810039300094038,
                -48.08909326974826
            ],
            [
                -15.80997865004702,
                -48.08892463487413
            ],
            [
                -15.80992182502351,
                -48.08881231743707
            ],
            [
                -15.809867912511756,
                -48.08872515871853
            ],
            [
                -15.809757,
                -48.0886
            ],
            [
                -15.809696,
                -48.0886
            ],
            [
                -15.809651,
                -48.088637
            ],
            [
                -15.809621,
                -48.088728
            ],
            [
                -15.809605,
                -48.088832
            ],
            [
                -15.809662,
                -48.08898966666666
            ],
            [
                -15.809719,
                -48.08914733333334
            ],
            [
                -15.809778,
                -48.08930525
            ],
            [
                -15.809837,
                -48.08946316666667
            ],
            [
                -15.809896,
                -48.089621083333334
            ],
            [
                -15.809928,
                -48.08974454166667
            ],
            [
                -15.80994,
                -48.08984527083334
            ],
            [
                -15.809925,
                -48.089998
            ],
            [
                -15.809884,
                -48.09003
            ],
            [
                -15.809827,
                -48.090067
            ],
            [
                -15.809723,
                -48.090115
            ],
            [
                -15.809666,
                -48.090167
            ],
            [
                -15.809534,
                -48.090212
            ],
            [
                -15.809410333333332,
                -48.090262333333335
            ],
            [
                -15.809286666666667,
                -48.09031266666667
            ],
            [
                -15.80914575,
                -48.090378
            ],
            [
                -15.809004833333333,
                -48.09044333333333
            ],
            [
                -15.808863916666667,
                -48.090508666666665
            ],
            [
                -15.808705458333334,
                -48.09058683333333
            ],
            [
                -15.808596305555556,
                -48.09064722222222
            ],
            [
                -15.808487152777777,
                -48.09070761111111
            ],
            [
                -15.808364114583334,
                -48.09078495833333
            ],
            [
                -15.808241076388889,
                -48.090862305555554
            ],
            [
                -15.808118038194443,
                -48.09093965277778
            ],
            [
                -15.807995692129628,
                -48.09102010185185
            ],
            [
                -15.807873346064815,
                -48.09110055092592
            ],
            [
                -15.807728897376544,
                -48.09120703395062
            ],
            [
                -15.80758444868827,
                -48.091313516975305
            ],
            [
                -15.807465299125514,
                -48.09140801131687
            ],
            [
                -15.807346149562756,
                -48.09150250565843
            ],
            [
                -15.807225074781378,
                -48.09160575282922
            ],
            [
                -15.807114537390689,
                -48.09170587641461
            ],
            [
                -15.807002903043017,
                -48.09181640731096
            ],
            [
                -15.806891268695345,
                -48.09192693820731
            ],
            [
                -15.806779634347672,
                -48.09203746910365
            ],
            [
                -15.806685756231781,
                -48.09213797940244
            ],
            [
                -15.80659187811589,
                -48.09223848970122
            ],
            [
                -15.806483939057944,
                -48.09236474485061
            ],
            [
                -15.80639062603863,
                -48.09247816323374
            ],
            [
                -15.806297313019314,
                -48.09259158161687
            ],
            [
                -15.806196696873698,
                -48.09273406995732
            ],
            [
                -15.806096080728082,
                -48.09287655829777
            ],
            [
                -15.805995464582466,
                -48.09301904663821
            ],
            [
                -15.805894848436848,
                -48.09316153497866
            ],
            [
                -15.805794232291232,
                -48.09330402331911
            ],
            [
                -15.805693616145616,
                -48.09344651165956
            ],
            [
                -15.805605846788014,
                -48.09357592638297
            ],
            [
                -15.805518077430412,
                -48.09370534110637
            ],
            [
                -15.805430308072808,
                -48.093834755829775
            ],
            [
                -15.805342538715205,
                -48.093964170553186
            ],
            [
                -15.805254769357603,
                -48.094093585276596
            ],
            [
                -15.805169015486083,
                -48.094221868221275
            ],
            [
                -15.805083261614563,
                -48.094350151165955
            ],
            [
                -15.80499750774304,
                -48.09447843411064
            ],
            [
                -15.80491175387152,
                -48.09460671705532
            ],
            [
                -15.804811578484369,
                -48.09475574534979
            ],
            [
                -15.804711403097217,
                -48.09490477364426
            ],
            [
                -15.804611227710064,
                -48.095053801938725
            ],
            [
                -15.804511052322912,
                -48.09520283023319
            ],
            [
                -15.80441087693576,
                -48.095351858527664
            ],
            [
                -15.804310701548609,
                -48.09550088682213
            ],
            [
                -15.804210526161457,
                -48.095649915116596
            ],
            [
                -15.804110350774303,
                -48.09579894341106
            ],
            [
                -15.804010175387152,
                -48.095947971705534
            ],
            [
                -15.803924783591434,
                -48.09607564780369
            ],
            [
                -15.803839391795718,
                -48.09620332390185
            ],
            [
                -15.803764695897858,
                -48.09631216195092
            ],
            [
                -15.803661780829279,
                -48.09646519495149
            ],
            [
                -15.803558865760698,
                -48.096618227952064
            ],
            [
                -15.803455950692118,
                -48.09677126095263
            ],
            [
                -15.80335303562354,
                -48.0969242939532
            ],
            [
                -15.803250120554958,
                -48.09707732695377
            ],
            [
                -15.803147205486379,
                -48.097230359954345
            ],
            [
                -15.8030442904178,
                -48.09738339295492
            ],
            [
                -15.802941375349219,
                -48.09753642595548
            ],
            [
                -15.80283846028064,
                -48.097689458956054
            ],
            [
                -15.80273554521206,
                -48.09784249195663
            ],
            [
                -15.802632630143481,
                -48.0979955249572
            ],
            [
                -15.8025297150749,
                -48.09814855795777
            ],
            [
                -15.802426800006321,
                -48.098301590958336
            ],
            [
                -15.802323884937742,
                -48.09845462395891
            ],
            [
                -15.802220969869161,
                -48.09860765695948
            ],
            [
                -15.802118054800582,
                -48.09876068996005
            ],
            [
                -15.802015139732003,
                -48.098913722960624
            ],
            [
                -15.801912224663422,
                -48.09906675596119
            ],
            [
                -15.801809309594843,
                -48.09921978896176
            ],
            [
                -15.801706394526263,
                -48.09937282196233
            ],
            [
                -15.801603479457683,
                -48.099525854962906
            ],
            [
                -15.801500564389103,
                -48.09967888796348
            ],
            [
                -15.801397649320524,
                -48.09983192096404
            ],
            [
                -15.801294734251943,
                -48.099984953964615
            ],
            [
                -15.801191819183364,
                -48.10013798696519
            ],
            [
                -15.801088904114785,
                -48.10029101996576
            ],
            [
                -15.800985989046206,
                -48.10044405296633
            ],
            [
                -15.800883073977625,
                -48.100597085966896
            ],
            [
                -15.800780158909046,
                -48.10075011896747
            ],
            [
                -15.800677243840466,
                -48.10090315196804
            ],
            [
                -15.800574328771885,
                -48.10105618496861
            ],
            [
                -15.800471413703306,
                -48.101209217969185
            ],
            [
                -15.800368498634727,
                -48.10136225096975
            ],
            [
                -15.800265583566146,
                -48.10151528397032
            ],
            [
                -15.800162668497567,
                -48.101668316970894
            ],
            [
                -15.800059753428988,
                -48.101821349971466
            ],
            [
                -15.799956838360407,
                -48.10197438297204
            ],
            [
                -15.799853923291828,
                -48.1021274159726
            ],
            [
                -15.799751008223248,
                -48.102280448973175
            ],
            [
                -15.799648093154667,
                -48.10243348197375
            ],
            [
                -15.799545178086088,
                -48.10258651497432
            ],
            [
                -15.799442263017509,
                -48.10273954797489
            ],
            [
                -15.79933934794893,
                -48.102892580975464
            ],
            [
                -15.799236432880349,
                -48.10304561397603
            ],
            [
                -15.79913351781177,
                -48.1031986469766
            ],
            [
                -15.79903060274319,
                -48.10335167997717
            ],
            [
                -15.79892768767461,
                -48.103504712977745
            ],
            [
                -15.79882477260603,
                -48.10365774597832
            ],
            [
                -15.798721857537451,
                -48.10381077897888
            ],
            [
                -15.79861894246887,
                -48.103963811979455
            ],
            [
                -15.798516027400291,
                -48.10411684498003
            ],
            [
                -15.798413112331712,
                -48.1042698779806
            ],
            [
                -15.798310197263131,
                -48.10442291098117
            ],
            [
                -15.798207282194552,
                -48.104575943981736
            ],
            [
                -15.798104367125973,
                -48.10472897698231
            ],
            [
                -15.798001452057392,
                -48.10488200998288
            ],
            [
                -15.797898536988813,
                -48.10503504298345
            ],
            [
                -15.797795621920233,
                -48.105188075984024
            ],
            [
                -15.797692706851652,
                -48.10534110898459
            ],
            [
                -15.797589791783073,
                -48.10549414198516
            ],
            [
                -15.797486876714494,
                -48.105647174985734
            ],
            [
                -15.797383961645915,
                -48.105800207986306
            ],
            [
                -15.797281046577334,
                -48.10595324098688
            ],
            [
                -15.797178131508755,
                -48.10610627398744
            ],
            [
                -15.797075216440176,
                -48.106259306988015
            ],
            [
                -15.796972301371595,
                -48.10641233998859
            ],
            [
                -15.796869386303015,
                -48.10656537298916
            ],
            [
                -15.796766471234436,
                -48.10671840598973
            ],
            [
                -15.796663556165855,
                -48.1068714389903
            ],
            [
                -15.796560641097276,
                -48.10702447199087
            ],
            [
                -15.796457726028697,
                -48.10717750499144
            ],
            [
                -15.796354810960116,
                -48.10733053799201
            ],
            [
                -15.796251895891537,
                -48.107483570992585
            ],
            [
                -15.796148980822958,
                -48.10763660399315
            ],
            [
                -15.796046065754377,
                -48.10778963699372
            ],
            [
                -15.795943150685797,
                -48.107942669994294
            ],
            [
                -15.795840235617218,
                -48.108095702994866
            ],
            [
                -15.795737320548639,
                -48.10824873599544
            ],
            [
                -15.795634405480058,
                -48.108401768996
            ],
            [
                -15.795531490411479,
                -48.108554801996576
            ],
            [
                -15.7954285753429,
                -48.10870783499715
            ],
            [
                -15.795325660274319,
                -48.10886086799772
            ],
            [
                -15.79522274520574,
                -48.10901390099829
            ],
            [
                -15.79511983013716,
                -48.10916693399886
            ],
            [
                -15.79501691506858,
                -48.10931996699943
            ],
            [
                -15.79492826255715,
                -48.109452139166194
            ],
            [
                -15.79483961004572,
                -48.10958431133295
            ],
            [
                -15.79475095753429,
                -48.10971648349971
            ],
            [
                -15.79466230502286,
                -48.109848655666475
            ],
            [
                -15.79457365251143,
                -48.10998082783324
            ],
            [
                -15.794476043759525,
                -48.11012602319437
            ],
            [
                -15.79437843500762,
                -48.110271218555496
            ],
            [
                -15.794280826255715,
                -48.110416413916624
            ],
            [
                -15.79418321750381,
                -48.110561609277745
            ],
            [
                -15.794085608751905,
                -48.11070680463887
            ],
            [
                -15.794004304375953,
                -48.11082640231943
            ],
            [
                -15.793930652187976,
                -48.110942701159715
            ],
            [
                -15.793877326093988,
                -48.11104435057986
            ],
            [
                -15.793838663046994,
                -48.11115517528993
            ],
            [
                -15.793816331523498,
                -48.11127558764497
            ],
            [
                -15.793817165761748,
                -48.111400293822484
            ],
            [
                -15.793839582880874,
                -48.11152364691124
            ],
            [
                -15.793884791440437,
                -48.11164382345562
            ],
            [
                -15.793968395720219,
                -48.111791911727806
            ],
            [
                -15.79407119786011,
                -48.1118869558639
            ],
            [
                -15.794207,
                -48.111976
            ],
            [
                -15.794235,
                -48.111961
            ],
            [
                -15.794242,
                -48.11192
            ],
            [
                -15.794217,
                -48.111855
            ],
            [
                -15.794189,
                -48.111773
            ],
            [
                -15.794131,
                -48.111691
            ],
            [
                -15.794084,
                -48.111587
            ],
            [
                -15.794057,
                -48.111427
            ],
            [
                -15.794067,
                -48.1113
            ],
            [
                -15.794109,
                -48.111173
            ],
            [
                -15.794190500000001,
                -48.11104725
            ],
            [
                -15.794272,
                -48.1109215
            ],
            [
                -15.7943535,
                -48.11079575
            ],
            [
                -15.794467,
                -48.110656
            ],
            [
                -15.794506,
                -48.110656
            ],
            [
                -15.794607,
                -48.110706
            ],
            [
                -15.794654,
                -48.110717
            ],
            [
                -15.794686,
                -48.110708
            ],
            [
                -15.794715,
                -48.11068
            ],
            [
                -15.794785000000001,
                -48.1105705
            ]
        ]
    }
}